Metadata-Version: 2.1
Name: kokosznicka
Version: 0.1
Summary: A simple and effective syllabificator for the Polish language.
Home-page: https://github.com/tytusdunin/kokosznicka
Download-URL: https://github.com/tytusdunin/kokosznicka/archive/refs/tags/v0.1.tar.gz
Author: Tytus Dunin
Author-email: tm.dunin@student.uw.edu.pl
License: GPL-3.0
Keywords: npl,syllabification,hyphenation,polish
Classifier: Development Status :: 4 - Beta
Classifier: Intended Audience :: Developers
Classifier: Topic :: Software Development :: Build Tools
Classifier: License :: OSI Approved :: GNU General Public License v3 (GPLv3)
Classifier: Programming Language :: Python :: 3
Classifier: Programming Language :: Python :: 3.4
Classifier: Programming Language :: Python :: 3.5
Classifier: Programming Language :: Python :: 3.6
License-File: LICENSE
